gdpyc/__init__.py
gdpyc/core.py
gdpyc/data.py
gdpyc/data/dust_ebv_Planck13_healpix_lowres.fits
gdpyc/data/dust_ebv_SFD_healpix_lowres.fits
gdpyc/data/h1_nh_DL_healpix_lowres.fits
gdpyc/data/h1_nh_DL_heasoft.fits
gdpyc/data/h1_nh_HI4PI_healpix_lowres.fits
gdpyc/data/h1_nh_LAB_healpix_lowres.fits
gdpyc/data/h1_nh_LAB_heasoft.fits
gdpyc/data/sfcoeff.fits
gdpyc-1.1.dist-info/LICENSE
gdpyc-1.1.dist-info/METADATA
gdpyc-1.1.dist-info/WHEEL
gdpyc-1.1.dist-info/top_level.txt
gdpyc-1.1.dist-info/RECORD
