Metadata-Version: 2.1
Name: gdpyc
Version: 1.1
Summary: Gas and Dust Python Calculator
Home-page: https://github.com/ruizca/gdpyc
Author: Angel Ruiz
Author-email: angel.ruizca@gmail.com
License: UNKNOWN
Platform: UNKNOWN
Classifier: Development Status :: 4 - Beta
Classifier: Intended Audience :: Science/Research
Classifier: Topic :: Scientific/Engineering :: Astronomy
Classifier: Programming Language :: Python :: 2.7
Classifier: Programming Language :: Python :: 3
Classifier: License :: OSI Approved :: BSD License
Classifier: Operating System :: POSIX :: Linux
Requires-Dist: astropy
Requires-Dist: numpy
Requires-Dist: astropy-healpix
Requires-Dist: regions
Provides-Extra: plot_map
Requires-Dist: matplotlib ; extra == 'plot_map'
Requires-Dist: healpy ; extra == 'plot_map'
